pakettic/__init__.py
pakettic/__main__.py
pakettic/ast.py
pakettic/main.py
pakettic/optimize.py
pakettic/parser.py
pakettic/printer.py
pakettic/ticfile.py
pakettic-1.4.1.dist-info/entry_points.txt
pakettic-1.4.1.dist-info/LICENSE
pakettic-1.4.1.dist-info/METADATA
pakettic-1.4.1.dist-info/WHEEL
pakettic-1.4.1.dist-info/RECORD
