Metadata-Version: 2.3
Name: pakettic
Version: 1.4.1
Summary: A tool for minifying and compressing TIC-80 fantasy console carts
License: MIT
Keywords: TIC-80,Fantasy Console,Compression,LUA
Author: Veikko Sariola
Author-email: 5684185+vsariola@users.noreply.github.com
Requires-Python: >=3.9,<4.0
Classifier: Development Status :: 5 - Production/Stable
Classifier: Environment :: Console
Classifier: License :: OSI Approved :: MIT License
Classifier: Programming Language :: Python :: 3
Classifier: Programming Language :: Python :: 3.9
Classifier: Programming Language :: Python :: 3.10
Classifier: Programming Language :: Python :: 3.11
Classifier: Programming Language :: Python :: 3.12
Classifier: Programming Language :: Python :: 3.13
Requires-Dist: pyparsing (>=3.0.8,<4.0.0)
Requires-Dist: tqdm (>=4.64.0,<5.0.0)
Requires-Dist: zopflipy (>=1.7,<2.0)
Project-URL: Repository, https://github.com/vsariola/pakettic
